bird_form/__init__.py
bird_form/core/__init__.py
bird_form/windows/__init__.py
bird_form/windows/app.py
bird_form/windows/button.py
bird_form/windows/panel.py
bird_form/windows/tab.py
bird_form/windows/widget.py
bird_form/windows/window.py
bird_dev_form-1.0.0a1.dist-info/METADATA
bird_dev_form-1.0.0a1.dist-info/WHEEL
bird_dev_form-1.0.0a1.dist-info/top_level.txt
bird_dev_form-1.0.0a1.dist-info/RECORD
